krwordrank/__init__.py
krwordrank/about.py
krwordrank/graph/__init__.py
krwordrank/graph/_rank.py
krwordrank/hangle/__init__.py
krwordrank/hangle/_hangle.py
krwordrank/sentence/__init__.py
krwordrank/sentence/_sentence.py
krwordrank/sentence/_tokenizer.py
krwordrank/word/__init__.py
krwordrank/word/_word.py
krwordrank-1.0.3.dist-info/LICENSE
krwordrank-1.0.3.dist-info/METADATA
krwordrank-1.0.3.dist-info/WHEEL
krwordrank-1.0.3.dist-info/top_level.txt
krwordrank-1.0.3.dist-info/RECORD
