Metadata-Version: 2.1
Name: krwordrank
Version: 1.0.3
Summary: KR-WordRank: Korean Unsupervised Word/Keyword Extractor
Home-page: https://github.com/lovit/KR-WordRank
Author: Lovit
Author-email: soy.lovit@gmail.com
License: UNKNOWN
Keywords: Korean word keyword extraction
Platform: UNKNOWN
